Workbook

Sheet how_to
A1: Rare Earth Intel - ground truth workbook v3
A3: SHEET ORDER OF USE
A4: 1. worklist - the 20 numbers to find, which page, and the trap each one tests
A5: 2. example_row - GT01 worked out, as a format reference. Do not copy it; rebuild it.
A6: 3. ground_truth - you type here. One number from the page = one row.
A7: 4. checks - live formulas. All must read PASS before you send the file.
A8: 5. lists - controlled vocabulary. Two metrics are missing on purpose.
A9: 6. sources - document registry.
A11: BEFORE YOU TYPE ANYTHING
A12: Read PDF p.47 (printed p.43). It defines every unit in this filing. Four things to note:
A13: - REO MT means contained REO; the concentrate is above 60% REO grade
A14: - NdPr MT is oxide-equivalent, metal converted at an assumed 1.20 ratio
... A42: If that one fails, one of those three rows has the wrong scale_factor.

Sheet worklist
A1: target_id | B1: filled? | C1: number as printed | D1: what it is | E1: period | F1: pdf_page | G1: printed_page | H1: trap this row tests
A2: GT01 | B2: yes | C2: 41,992 | D2: Rare earth concentrate revenue | E2: FY2025 | F2: 48 | G2: 44 | H2: Scale. Table header says 'in thousands' -> scale_factor 1000.
A3: GT02 | B3: yes | C3: 144,363 | D3: Rare earth concentrate revenue | E3: FY2024 | F3: 48 | G3: 44 | H3: Comparative. period=FY2024 but source_document stays the FY2025 file. is_comparative TRUE.
A4: GT03 | B4: yes | C4: 252,468 | D4: Rare earth concentrate revenue | E4: FY2023 | F4: 48 | G4: 44 | H4: Comparative.
A5: GT04 | B5: yes | C5: 50,692 | D5: REO Production Volume (MTs) | E5: FY2025 | F5: 53 | G5: 49 | H5: Production, not sales. Different metric from GT05. MP produced 50,692 and sold 8,922.
A6: GT05 | B6: yes | C6: 8,922 | D6: REO Sales Volume (MTs) | E6: FY2025 | F6: 53 | G6: 49 | H6: Basis. MT = contained REO, concentrate is >60% grade, so ~14,900 t physical. basis=contained_REO.
A7: GT06 | B7: yes | C7: 32,703 | D7: REO Sales Volume (MTs) | E7: FY2024 | F7: 53 | G7: 49 | H7: Comparative + basis.
A8: GT07 | B8: yes | C8: 4,707 | D8: Realized Price per REO MT | E8: FY2025 | F8: 53 | G8: 49 | H8: Basket price across the whole REO mix incl. Ce and La. price_basis=basket. Scale is 1 here, not 1000.
A9: GT08 | B9: yes | C9: 6,854 | D9: Realized Price per REO MT | E9: FY2023 | F9: 53 | G9: 49 | H9: Comparative + basket.
A10: GT09 | B10: yes | C10: 115,131 | D10: NdPr oxide and metal revenue | E10: FY2025 | F10: 48 | G10: 44 | H10: Blended line spanning two chain stages. Use chain_stage=oxide, basis=oxide_equivalent, confidence=low, explain in notes.
A11: GT10 | B11: yes | C11: 695 | D11: NdPr oxide and metal revenue | E11: FY2023 | F11: 48 | G11: 44 | H11: Small number, still in thousands. Easy to record as 695 dollars.
A12: GT11 | B12: yes | C12: 2,599 | D12: NdPr Production Volume (MTs) | E12: FY2025 | F12: 53 | G12: 49 | H12: Production not sales.
A13: GT12 | B13: yes | C13: 1,994 | D13: NdPr Sales Volume (MTs) | E13: FY2025 | F13: 53 | G13: 49 | H13: Oxide-equivalent. Metal converted at assumed 1.20 ratio. Partly a modelling assumption. Also includes intercompany sales from Q4 2025 - say so in notes.
... A21: GT20 | B21: yes | C21: 51,016 | D21: Price protection agreement income | E21: FY2025 | F21: 53 | G21: 49 | H21: Money outside revenue. In thousands. METRIC NOT IN VOCABULARY - add it yourself.
A22: All 20 come from mp-materials_10k_FY2025.pdf (Workiva original, 121 pages). pdf_page = printed_page + 4 throughout this file.
A23: All 20 come from mp-materials_10k_FY2025.pdf. Fill ground_truth yourself - this sheet only says which number to find and what it is testing.

Sheet lists
A1: material | B1: metric | C1: chain_stage | D1: basis | E1: entity_scope | F1: price_basis | G1: derivation | H1: period_granularity | I1: unit | J1: currency | K1: doc_type | L1: language | M1: confidence | N1: is_comparative
A2: NdPr | B2: production_volume | C2: ore | D2: contained_REO | E2: consolidated | F2: basket | G2: as_reported | H2: FY | I2: tonnes | J2: USD | K2: annual | L2: en | M2: high | N2: TRUE
A3: Nd | B3: sales_volume | C3: concentrate | D3: oxide_equivalent | E3: segment | F3: single_material | G3: derived | H3: H1 | I3: kg | J3: AUD | K3: financial | L3: zh | M3: low | N3: FALSE
A4: Pr | B4: revenue | C4: oxide | D4: gross_weight | E4: subsidiary | F4: contract | H4: H2 | I4: USD | J4: RMB | K4: quarterly | L4: other
A5: Dy | B5: avg_selling_price | C5: metal | D5: dry_weight | E5: site | F5: floor_supported | H5: Q1 | I5: AUD | J5: INR | K5: agency
A6: Tb | B6: purchase_price | C6: alloy | D6: not_applicable | E6: country | F6: not_applicable | H6: Q2 | I6: RMB | J6: CAD | K6: technical_report
A7: Ce | B7: inventory_volume | C7: sintered_magnet | E7: global | H7: Q3 | I7: INR | J7: none
A8: La | B8: capacity | C8: not_applicable | H8: Q4 | I8: USD_per_tonne
A9: Sm | B9: grams_per_kg | H9: CY | I9: USD_per_kg
A10: Gd | B10: composition_pct | H10: multi_year | I10: AUD_per_kg
A11: total_REO | B11: reserve_tonnage | I11: RMB_per_tonne
A12: NdFeB | B12: grade_pct | I12: RMB_per_kg
A13: mixed_REC | B13: intersegment_elimination | I13: INR_per_kg
A14: other | B14: non_revenue_income | I14: g_per_kg
A15: not_applicable | I15: percent
A17: Vocabulary extended in v4: metric += intersegment_elimination (GT15), non_revenue_income (GT20); material += not_applicable (GT16, GT17 - totals spanning all products). Dropdown ranges extended to match.
A18: Add them to the metric column yourself, then extend the dropdown range. Extending the vocabulary is correct; free-typing into a row is not.

Sheet ground_truth
A1: row_id | B1: entity | C1: entity_scope | D1: segment | E1: material | F1: chain_stage | G1: metric | H1: basis | I1: period | J1: period_granularity | K1: period_end_date | L1: value_reported | M1: scale_factor | N1: value_base | O1: unit | P1: currency | Q1: price_basis | R1: derivation | S1: derived_from | T1: is_comparative | U1: doc_type | V1: source_document | W1: pdf_page | X1: printed_page | Y1: raw_text | Z1: language | AA1: confidence | AB1: notes
A2: GT01 | B2: MP Materials | C2: segment | D2: Materials | E2: total_REO | F2: concentrate | G2: revenue | H2: contained_REO | I2: FY2025 | J2: FY | K2: 2025-12-31 | L2: 41992 | M2: 1000 | N2: =IF(L2="","",L2*M2) -> 41992000 | O2: USD | P2: USD | Q2: not_applicable | R2: as_reported | T2: FALSE | U2: annual | V2: mp-materials_10k_FY2025.pdf | W2: 48 | X2: 44 | Y2: $ 41,992 | Z2: en | AA2: high | AB2: Table header 'in thousands'. Concentrate is sold only by the Materials segment, so the consolidated product line equals the segment figure. Pairs with GT05/GT07.
A3: GT02 | B3: MP Materials | C3: segment | D3: Materials | E3: total_REO | F3: concentrate | G3: revenue | H3: contained_REO | I3: FY2024 | J3: FY | K3: 2024-12-31 | L3: 144363 | M3: 1000 | N3: =IF(L3="","",L3*M3) -> 144363000 | O3: USD | P3: USD | Q3: not_applicable | R3: as_reported | T3: TRUE | U3: annual | V3: mp-materials_10k_FY2025.pdf | W3: 48 | X3: 44 | Y3: $ 144,363 | Z3: en | AA3: high | AB3: Prior-year comparative inside the FY2025 filing. Not yet checked against the FY2024 10-K's own figure (restatement check pending).
A4: GT03 | B4: MP Materials | C4: segment | D4: Materials | E4: total_REO | F4: concentrate | G4: revenue | H4: contained_REO | I4: FY2023 | J4: FY | K4: 2023-12-31 | L4: 252468 | M4: 1000 | N4: =IF(L4="","",L4*M4) -> 252468000 | O4: USD | P4: USD | Q4: not_applicable | R4: as_reported | T4: TRUE | U4: annual | V4: mp-materials_10k_FY2025.pdf | W4: 48 | X4: 44 | Y4: $ 252,468 | Z4: en | AA4: high | AB4: Comparative. Not yet checked against the FY2023 10-K.
A5: GT04 | B5: MP Materials | C5: segment | D5: Materials | E5: total_REO | F5: concentrate | G5: production_volume | H5: contained_REO | I5: FY2025 | J5: FY | K5: 2025-12-31 | L5: 50692 | M5: 1 | N5: =IF(L5="","",L5*M5) -> 50692 | O5: tonnes | P5: none | Q5: not_applicable | R5: as_reported | T5: FALSE | U5: annual | V5: mp-materials_10k_FY2025.pdf | W5: 53 | X5: 49 | Y5: 50,692 | Z5: en | AA5: high | AB5: PRODUCTION, not sales. MT of contained REO (p.43). Only 8,922 sold (GT05): concentrate sales to China ceased July 2025 and most output was refined internally into NdPr. Not a stockpile.
A6: GT05 | B6: MP Materials | C6: segment | D6: Materials | E6: total_REO | F6: concentrate | G6: sales_volume | H6: contained_REO | I6: FY2025 | J6: FY | K6: 2025-12-31 | L6: 8922 | M6: 1 | N6: =IF(L6="","",L6*M6) -> 8922 | O6: tonnes | P6: none | Q6: not_applicable | R6: as_reported | T6: FALSE | U6: annual | V6: mp-materials_10k_FY2025.pdf | W6: 53 | X6: 49 | Y6: 8,922 | Z6: en | AA6: high | AB6: MT of contained REO, not physical concentrate. Grade >60% REO per dry MT (p.43), so physical weight is materially higher. Do not compare with customs tonnage without regrading.
A7: GT06 | B7: MP Materials | C7: segment | D7: Materials | E7: total_REO | F7: concentrate | G7: sales_volume | H7: contained_REO | I7: FY2024 | J7: FY | K7: 2024-12-31 | L7: 32703 | M7: 1 | N7: =IF(L7="","",L7*M7) -> 32703 | O7: tonnes | P7: none | Q7: not_applicable | R7: as_reported | T7: TRUE | U7: annual | V7: mp-materials_10k_FY2025.pdf | W7: 53 | X7: 49 | Y7: 32,703 | Z7: en | AA7: high | AB7: Comparative. Contained-REO basis as GT05.
A8: GT07 | B8: MP Materials | C8: segment | D8: Materials | E8: total_REO | F8: concentrate | G8: avg_selling_price | H8: contained_REO | I8: FY2025 | J8: FY | K8: 2025-12-31 | L8: 4707 | M8: 1 | N8: =IF(L8="","",L8*M8) -> 4707 | O8: USD_per_tonne | P8: USD | Q8: basket | R8: as_reported | T8: FALSE | U8: annual | V8: mp-materials_10k_FY2025.pdf | W8: 53 | X8: 49 | Y8: $ 4,707 | Z8: en | AA8: high | AB8: BASKET price across the whole REO mix incl. ~50% Ce and ~32% La (GT19). Never chart against an NdPr price. Issuer computes it as concentrate revenue / REO sales volume (p.43) but prints it, so as_reported. KPI table is 'in whole units' -> scale 1. Series discontinued after FY2025.
A9: GT08 | B9: MP Materials | C9: segment | D9: Materials | E9: total_REO | F9: concentrate | G9: avg_selling_price | H9: contained_REO | I9: FY2023 | J9: FY | K9: 2023-12-31 | L9: 6854 | M9: 1 | N9: =IF(L9="","",L9*M9) -> 6854 | O9: USD_per_tonne | P9: USD | Q9: basket | R9: as_reported | T9: TRUE | U9: annual | V9: mp-materials_10k_FY2025.pdf | W9: 53 | X9: 49 | Y9: $ 6,854 | Z9: en | AA9: high | AB9: Comparative. Basket price, as GT07.
A10: GT09 | B10: MP Materials | C10: segment | D10: Materials | E10: NdPr | F10: oxide | G10: revenue | H10: oxide_equivalent | I10: FY2025 | J10: FY | K10: 2025-12-31 | L10: 115131 | M10: 1000 | N10: =IF(L10="","",L10*M10) -> 115131000 | O10: USD | P10: USD | Q10: not_applicable | R10: as_reported | T10: FALSE | U10: annual | V10: mp-materials_10k_FY2025.pdf | W10: 48 | X10: 44 | Y10: 115,131 | Z10: en | AA10: low | AB10: BLENDED line 'NdPr oxide and metal' spans two chain stages; no honest single chain_stage. Project decision: oxide + oxide_equivalent + low confidence. Gross of the 2,789 intersegment elimination (GT15); includes Q4 2025 sales to Magnetics. Pair only with GT12, never net GT15 out of this alone.
A11: GT10 | B11: MP Materials | C11: segment | D11: Materials | E11: NdPr | F11: oxide | G11: revenue | H11: oxide_equivalent | I11: FY2023 | J11: FY | K11: 2023-12-31 | L11: 695 | M11: 1000 | N11: =IF(L11="","",L11*M11) -> 695000 | O11: USD | P11: USD | Q11: not_applicable | R11: as_reported | T11: TRUE | U11: annual | V11: mp-materials_10k_FY2025.pdf | W11: 48 | X11: 44 | Y11: 695 | Z11: en | AA11: low | AB11: Comparative. In thousands: this is USD 695,000, not USD 695. Same blended line as GT09. Pairs with GT13 (10 MT) - any price derived from this pair is meaningless.
A12: GT11 | B12: MP Materials | C12: segment | D12: Materials | E12: NdPr | F12: oxide | G12: production_volume | H12: gross_weight | I12: FY2025 | J12: FY | K12: 2025-12-31 | L12: 2599 | M12: 1 | N12: =IF(L12="","",L12*M12) -> 2599 | O12: tonnes | P12: none | Q12: not_applicable | R12: as_reported | T12: FALSE | U12: annual | V12: mp-materials_10k_FY2025.pdf | W12: 53 | X12: 49 | Y12: 2,599 | Z12: en | AA12: high | AB12: Per p.43 this is finished, packaged NdPr OXIDE actually produced - physical tonnes of product, hence gross_weight. NOT the same basis as NdPr Sales Volume (GT12, oxide-equivalent). Production not sales.
A13: GT12 | B13: MP Materials | C13: segment | D13: Materials | E13: NdPr | F13: oxide | G13: sales_volume | H13: oxide_equivalent | I13: FY2025 | J13: FY | K13: 2025-12-31 | L13: 1994 | M13: 1 | N13: =IF(L13="","",L13*M13) -> 1994 | O13: tonnes | P13: none | Q13: not_applicable | R13: as_reported | T13: FALSE | U13: annual | V13: mp-materials_10k_FY2025.pdf | W13: 53 | X13: 49 | Y13: 1,994 | Z13: en | AA13: low | AB13: Oxide-equivalent: metal sales converted at an ASSUMED 1.20 ratio (100 MT metal = 120 MT here), so partly a modelling assumption. From Q4 2025 includes intercompany sales to Magnetics (p.43).
... A15: GT14 | B15: MP Materials | C15: segment | D15: Magnetics | E15: NdPr | F15: metal | G15: revenue | H15: not_applicable | I15: FY2025 | J15: FY | K15: 2025-12-31 | L15: 66861 | M15: 1000 | N15: =IF(L15="","",L15*M15) -> 66861000 | O15: USD | P15: USD | Q15: not_applicable | R15: as_reported | T15: FALSE | U15: annual | V15: mp-materials_10k_FY2025.pdf | W15: 48 | X15: 44 | Y15: 66,861 | Z15: en | AA15: high | AB15: MAGNETICS segment. NdPr metal from the Independence Facility sold to GM. No volume disclosed -> no implied price derivable. Recognised under a bill-and-hold arrangement (Note 16, printed p.96): GM owns it, MP still holds it.
A16: GT15 | B16: MP Materials | C16: consolidated | E16: NdPr | F16: oxide | G16: intersegment_elimination | H16: not_applicable | I16: FY2025 | J16: FY | K16: 2025-12-31 | L16: -2789 | M16: 1000 | N16: =IF(L16="","",L16*M16) -> -2789000 | O16: USD | P16: USD | Q16: not_applicable | R16: as_reported | T16: FALSE | U16: annual | V16: mp-materials_10k_FY2025.pdf | W16: 48 | X16: 44 | Y16: (2,789) | Z16: en | AA16: high | AB16: Negative: printed in parentheses. Footnote: elimination of NdPr oxide sold by Materials to Magnetics. Exists only at consolidated level. New metric added to lists.
A17: GT16 | B17: MP Materials | C17: consolidated | E17: not_applicable | F17: not_applicable | G17: revenue | H17: not_applicable | I17: FY2025 | J17: FY | K17: 2025-12-31 | L17: 224441 | M17: 1000 | N17: =IF(L17="","",L17*M17) -> 224441000 | O17: USD | P17: USD | Q17: not_applicable | R17: as_reported | T17: FALSE | U17: annual | V17: mp-materials_10k_FY2025.pdf | W17: 48 | X17: 44 | Y17: $ 224,441 | Z17: en | AA17: high | AB17: CONSOLIDATED total across all products. Pair against GT17. Bridge: 160,369 + 66,861 - 2,789 = 224,441 (ties exactly). Never divide by a segment volume.
A18: GT17 | B18: MP Materials | C18: segment | D18: Materials | E18: not_applicable | F18: not_applicable | G18: revenue | H18: not_applicable | I18: FY2025 | J18: FY | K18: 2025-12-31 | L18: 160369 | M18: 1000 | N18: =IF(L18="","",L18*M18) -> 160369000 | O18: USD | P18: USD | Q18: not_applicable | R18: as_reported | T18: FALSE | U18: annual | V18: mp-materials_10k_FY2025.pdf | W18: 100 | X18: 96 | Y18: 160,369 | Z18: en | AA18: high | AB18: Materials SEGMENT total, from Note 16 Revenue Recognition (printed p.96; project notes wrongly call this the segment note). Also on printed p.49. USD 64m below GT16: pairing segment volume with GT16 overstates price ~40%.
A19: GT18 | B19: MP Materials | C19: site | E19: NdPr | F19: concentrate | G19: composition_pct | H19: contained_REO | I19: not_applicable | L19: 15.7 | M19: 1 | N19: =IF(L19="","",L19*M19) -> 15.7 | O19: percent | P19: none | Q19: not_applicable | R19: as_reported | T19: FALSE | U19: annual | V19: mp-materials_10k_FY2025.pdf | W19: 33 | X19: 29 | Y19: 15.7 % | Z19: en | AA19: high | AB19: Convention: stored as percentage points (15.7, not 0.157). Estimated share of TREO content in Mountain Pass concentrate; 'natural distribution', stable over time. Same figure recurs on printed pp.32 and 34 inside reserve assumptions - cite the table on p.29.
A20: GT19 | B20: MP Materials | C20: site | E20: Ce | F20: concentrate | G20: composition_pct | H20: contained_REO | I20: not_applicable | L20: 50.2 | M20: 1 | N20: =IF(L20="","",L20*M20) -> 50.2 | O20: percent | P20: none | Q20: not_applicable | R20: as_reported | T20: FALSE | U20: annual | V20: mp-materials_10k_FY2025.pdf | W20: 33 | X20: 29 | Y20: 50.2 % | Z20: en | AA20: high | AB20: Half the REO is near-worthless cerium - the reason basket prices (GT07/GT08) mislead. Percentage points, as GT18.
A21: GT20 | B21: MP Materials | C21: segment | D21: Materials | E21: NdPr | F21: oxide | G21: non_revenue_income | H21: not_applicable | I21: FY2025 | J21: FY | K21: 2025-12-31 | L21: 51016 | M21: 1000 | N21: =IF(L21="","",L21*M21) -> 51016000 | O21: USD | P21: USD | Q21: not_applicable | R21: as_reported | T21: FALSE | U21: annual | V21: mp-materials_10k_FY2025.pdf | W21: 53 | X21: 49 | Y21: $ 51,016 | Z21: en | AA21: high | AB21: Price Protection Agreement income, booked OUTSIDE revenue. PPA ($110/kg NdPr floor from 1 Oct 2025) pays on NdPr products sold OR produced and stockpiled - a different volume base from GT12, so do not add it to GT09 and divide. New metric added to lists.
N22: =IF(L22="","",L22*M22)
N23: =IF(L23="","",L23*M23)
N24: =IF(L24="","",L24*M24)
N25: =IF(L25="","",L25*M25)
N26: =IF(L26="","",L26*M26)
N27: =IF(L27="","",L27*M27)
N28: =IF(L28="","",L28*M28)
N29: =IF(L29="","",L29*M29)
N30: =IF(L30="","",L30*M30)
N31: =IF(L31="","",L31*M31)
N32: =IF(L32="","",L32*M32)
N33: =IF(L33="","",L33*M33)
... N200: =IF(L200="","",L200*M200)

Sheet checks
A1: Live checks - all should read 0 (or PASS) before you send the file
A2: # | B2: Check | C2: Result | D2: Verdict | E2: What to do if it fires
A3: 1 | B3: Rows in tonnes or kg with blank basis | C3: =COUNTIFS(ground_truth!$O$2:$O$200,"tonnes",ground_truth!$H$2:$H$200,"")+COUNTIFS(ground_truth!$O$2:$O$200,"kg",ground_truth!$H$2:$H$200,"") -> 0 | D3: =IF(C3=0,"PASS","FIX") -> PASS | E3: Concentrate rows are contained_REO. NdPr rows are oxide_equivalent. Never not_applicable for a tonnage.
A4: 2 | B4: Volume rows not marked entity_scope = segment | C4: =COUNTIFS(ground_truth!$G$2:$G$200,"*volume*",ground_truth!$C$2:$C$200,"<>segment") -> 0 | D4: =IF(C4=0,"PASS","FIX") -> PASS | E4: Every volume KPI in this filing is Materials segment. Check the heading above the table.
A5: 3 | B5: Non-FY2025 rows not marked is_comparative = TRUE (period not_applicable excluded) | C5: =SUMPRODUCT((ground_truth!$A$2:$A$200<>"")*(ground_truth!$I$2:$I$200<>"")*(ground_truth!$I$2:$I$200<>"FY2025")*(ground_truth!$I$2:$I$200<>"not_applicable")*(UPPER(ground_truth!$T$2:$T$200&"")<>"TRUE")) -> 0 | D5: =IF(C5=0,"PASS","FIX") -> PASS | E5: A FY2024 figure inside a FY2025 filing is a comparative. period changes, source_document does not.
A6: 4 | B6: Rows marked derivation = derived | C6: =COUNTIF(ground_truth!$R$2:$R$200,"derived") -> 0 | D6: =IF(C6=0,"PASS","FIX") -> PASS | E6: All 20 are copied, not calculated. If you did arithmetic, you left the ground truth and entered analysis.
A7: 5 | B7: as_reported rows with empty raw_text | C7: =COUNTIFS(ground_truth!$A$2:$A$200,"<>",ground_truth!$R$2:$R$200,"as_reported",ground_truth!$Y$2:$Y$200,"") -> 0 | D7: =IF(C7=0,"PASS","FIX") -> PASS | E7: raw_text is not optional. Copy the string exactly as printed, including $ and commas.
A8: 6 | B8: Revenue rows with value_base under 100,000 (missed scale) | C8: =COUNTIFS(ground_truth!$G$2:$G$200,"revenue",ground_truth!$N$2:$N$200,"<100000",ground_truth!$N$2:$N$200,"<>") -> 0 | D8: =IF(C8=0,"PASS","FIX") -> PASS | E8: A revenue line printed 'in thousands' needs scale_factor 1000. GT10 (695) is the one most likely to trip this.
A9: 7 | B9: unit says USD_per_* but currency is not USD | C9: =COUNTIFS(ground_truth!$O$2:$O$200,"USD_per*",ground_truth!$P$2:$P$200,"<>USD") -> 0 | D9: =IF(C9=0,"PASS","FIX") -> PASS | E9: unit and currency must agree where unit names a currency.
A10: 8 | B10: total_REO priced as single_material | C10: =COUNTIFS(ground_truth!$E$2:$E$200,"total_REO",ground_truth!$G$2:$G$200,"*price*",ground_truth!$Q$2:$Q$200,"single_material") -> 0 | D10: =IF(C10=0,"PASS","FIX") -> PASS | E10: A price covering the whole REO mix is a basket price.
A11: 9 | B11: Targets from worklist still unfilled | C11: =20-COUNTIF(worklist!$B$2:$B$21,"yes") -> 0 | D11: =IF(C11=0,"PASS","FIX") -> PASS | E11: Counts worklist column B = "yes". Mark each target yes once its GT row is in ground_truth.
B13: Arithmetic reconciliation (GT01 / GT05 should equal GT07)
B14: Concentrate revenue FY2025, base units | C14: =IFERROR(SUMIFS(ground_truth!$N$2:$N$200,ground_truth!$G$2:$G$200,"revenue",ground_truth!$F$2:$F$200,"concentrate",ground_truth!$I$2:$I$200,"FY2025"),0) -> 41992000
B15: REO sales volume FY2025, tonnes | C15: =IFERROR(SUMIFS(ground_truth!$N$2:$N$200,ground_truth!$G$2:$G$200,"sales_volume",ground_truth!$F$2:$F$200,"concentrate",ground_truth!$I$2:$I$200,"FY2025"),0) -> 8922
B16: Implied price, USD per tonne | C16: =IFERROR(C14/C15,"") -> 4706.568
B17: Stated realized price FY2025 (GT07) | C17: =IFERROR(SUMIFS(ground_truth!$N$2:$N$200,ground_truth!$G$2:$G$200,"avg_selling_price",ground_truth!$F$2:$F$200,"concentrate",ground_truth!$I$2:$I$200,"FY2025"),0) -> 4707
B18: Difference | C18: =IFERROR(ABS(C16-C17)/C17,"") -> 9.1770964e-05 | D18: =IF(C18="","",IF(C18<0.0001,"PASS","FIX")) -> PASS | E18: Should be under 0.01%. If it is not, one of GT01, GT05 or GT07 has a scale_factor error.

Sheet example_row
A1: row_id | B1: entity | C1: entity_scope | D1: segment | E1: material | F1: chain_stage | G1: metric | H1: basis | I1: period | J1: period_granularity | K1: period_end_date | L1: value_reported | M1: scale_factor | N1: value_base | O1: unit | P1: currency | Q1: price_basis | R1: derivation | S1: derived_from | T1: is_comparative | U1: doc_type | V1: source_document | W1: pdf_page | X1: printed_page | Y1: raw_text | Z1: language | AA1: confidence | AB1: notes
A2: EXAMPLE | B2: MP Materials | C2: segment | D2: Materials | E2: total_REO | F2: concentrate | G2: revenue | H2: contained_REO | I2: FY2025 | J2: FY | K2: 2025-12-31 | L2: 41992 | M2: 1000 | N2: =L2*M2 -> 41992000 | O2: USD | P2: USD | Q2: not_applicable | R2: as_reported | T2: FALSE | U2: annual | V2: mp-materials_10k_FY2025.pdf | W2: 48 | X2: 44 | Y2: $ 41,992 | Z2: en | AA2: high | AB2: Format reference only. This is GT01 worked out. Do not copy it into ground_truth - build it yourself from p.88 so you see where every field comes from.

Sheet sources
A1: source_document | B1: entity | C1: doc_type | D1: period_covered | E1: url | F1: accession_or_id | G1: retrieved_date | H1: pages | I1: has_text_layer | J1: language | K1: notes
A2: mp-materials_10k_FY2025.pdf | B2: MP Materials | C2: annual | D2: FY2023-FY2025 | E2: https://www.sec.gov/Archives/edgar/data/1801368/000180136826000008/mp-20251231.htm | F2: 0001801368-26-000008 | H2: 121 | I2: YES | J2: en | K2: Original Workiva PDF (producer: Wdesk Fidelity Content Translations), real text layer, 121 pages. Replaces the earlier browser Print-to-PDF copy (221 rasterised pages). pdf_page = printed_page + 4 throughout. retrieved_date left blank: fill with your actual download date. SHA-256: c28ed1338d6ff136b8de06ad6ef768613dec44968cb88e4e00db9779b0f104a1
